processcube_client/__init__.py
processcube_client/client_factory.py
processcube_client/app_info/__init__.py
processcube_client/app_info/app_info_client.py
processcube_client/core/__init__.py
processcube_client/core/base_client.py
processcube_client/core/loop_helper.py
processcube_client/core/api/__init__.py
processcube_client/core/api/base_client.py
processcube_client/core/api/client.py
processcube_client/core/api/helpers/__init__.py
processcube_client/core/api/helpers/application_info.py
processcube_client/core/api/helpers/data_object_instances.py
processcube_client/core/api/helpers/empty_tasks.py
processcube_client/core/api/helpers/events.py
processcube_client/core/api/helpers/external_tasks.py
processcube_client/core/api/helpers/flow_node_instances.py
processcube_client/core/api/helpers/manual_tasks.py
processcube_client/core/api/helpers/process_definitions.py
processcube_client/core/api/helpers/process_instances.py
processcube_client/core/api/helpers/process_models.py
processcube_client/core/api/helpers/user_tasks.py
processcube_client/event/__init__.py
processcube_client/event/event_client.py
processcube_client/external_task/__init__.py
processcube_client/external_task/client_wrapper.py
processcube_client/external_task/external_task_client.py
processcube_client/external_task/external_task_worker.py
processcube_client/external_task/functional_error.py
processcube_client/flow_node_instance/__init__.py
processcube_client/flow_node_instance/flow_node_instance_client.py
processcube_client/notification/__init__.py
processcube_client/notification/notification_client.py
processcube_client/process_definition/__init__.py
processcube_client/process_definition/process_definition_client.py
processcube_client/process_definition/start_callback_type.py
processcube_client/process_instance/__init__.py
processcube_client/process_instance/process_instance_client.py
processcube_client/user_task/__init__.py
processcube_client/user_task/user_task_client.py
tests/__init__.py
processcube_client-6.1.0.dist-info/METADATA
processcube_client-6.1.0.dist-info/WHEEL
processcube_client-6.1.0.dist-info/top_level.txt
processcube_client-6.1.0.dist-info/RECORD
