Metadata-Version: 2.4
Name: processcube_client
Version: 6.1.0
Summary: A Client for the workflow engine of the ProcessCube platform.
Home-page: https://github.com/5minds/processcube_client.py
Author: 5Minds IT-Solutions GmbH & Co. KG
Author-email: ProcessCube@5Minds.de
Keywords: workflow-engine atlas-engine client bpmn
Classifier: Programming Language :: Python :: 3
Classifier: License :: OSI Approved :: MIT License
Classifier: Operating System :: OS Independent
Requires-Dist: aiohttp>=3.9.0
Requires-Dist: nest-asyncio==1.5.6
Requires-Dist: dataclasses-json>=0.6.0
Requires-Dist: requests>=2.28.1
Dynamic: author
Dynamic: author-email
Dynamic: classifier
Dynamic: description
Dynamic: description-content-type
Dynamic: home-page
Dynamic: keywords
Dynamic: requires-dist
Dynamic: summary
